pymccrgb/__init__.py
pymccrgb/api.py
pymccrgb/classification.py
pymccrgb/colorize.py
pymccrgb/core.py
pymccrgb/datasets.py
pymccrgb/features.py
pymccrgb/ioutils.py
pymccrgb/plotting.py
pymccrgb/pointutils.py
pymccrgb/tests/context.py
pymccrgb/tests/test_core.py
pymccrgb/tests/test_features.py
pymccrgb/tests/data/points_rgb.laz
pymccrgb-0.1.5.data/data/LICENSE
pymccrgb-0.1.5.dist-info/LICENSE
pymccrgb-0.1.5.dist-info/METADATA
pymccrgb-0.1.5.dist-info/WHEEL
pymccrgb-0.1.5.dist-info/dependency_links.txt
pymccrgb-0.1.5.dist-info/top_level.txt
pymccrgb-0.1.5.dist-info/RECORD
