Metadata-Version: 2.1
Name: pymccrgb
Version: 0.1.5
Summary: A Python package for point cloud classification using color and curvature
Home-page: https://github.com/rmsare/pymccrgb
Author: ['Robert Sare', 'George Hilley']
Author-email: rmsare@stanford.edu
License: MIT
Platform: UNKNOWN
Classifier: Development Status :: 4 - Beta
Classifier: Intended Audience :: Developers
Classifier: Intended Audience :: Science/Research
Classifier: Programming Language :: Python :: 3
Classifier: License :: OSI Approved :: MIT License
Classifier: Operating System :: OS Independent
Requires-Dist: cmake
Requires-Dist: cython
Requires-Dist: fiona
Requires-Dist: numpy
Requires-Dist: matplotlib
Requires-Dist: pdal
Requires-Dist: scipy
Requires-Dist: scikit-image
Requires-Dist: scikit-learn
